inventory_cli/__init__.py
inventory_cli/cli.py
inventory_cli/main.py
inventory_cli/api/__init__.py
inventory_cli/api/cli.py
inventory_cli/api/database.py
inventory_cli/api/models.py
inventory_cli/api/router.py
inventory_cli_tool-0.0.8.dist-info/METADATA
inventory_cli_tool-0.0.8.dist-info/WHEEL
inventory_cli_tool-0.0.8.dist-info/entry_points.txt
inventory_cli_tool-0.0.8.dist-info/top_level.txt
inventory_cli_tool-0.0.8.dist-info/RECORD
